a2ahub/__init__.py
a2ahub/main.py
a2ahub-0.1.0.dist-info/licenses/LICENSE
a2ahub-0.1.0.dist-info/METADATA
a2ahub-0.1.0.dist-info/WHEEL
a2ahub-0.1.0.dist-info/entry_points.txt
a2ahub-0.1.0.dist-info/top_level.txt
a2ahub-0.1.0.dist-info/RECORD
